pyCandle.pypy37-pp73-x86_64-linux-gnu.so
pyCandleMAB-1.6.0.dist-info/LICENSE.txt
pyCandleMAB-1.6.0.dist-info/WHEEL
pyCandleMAB-1.6.0.dist-info/RECORD
pyCandleMAB-1.6.0.dist-info/top_level.txt
pyCandleMAB-1.6.0.dist-info/METADATA
