Metadata-Version: 2.1
Name: pyCandleMAB
Version: 1.6.0
Summary: Python package for controlling MD80-based actuators
Author: MAB Robotics
Author-email: support.md80@mabrobotics.pl
Classifier: License :: OSI Approved :: GNU General Public License v3 (GPLv3)
Classifier: Natural Language :: English
Classifier: Programming Language :: Python :: 3.6
Classifier: Programming Language :: Python :: 3.7
Classifier: Programming Language :: Python :: 3.8
Classifier: Programming Language :: Python :: 3.9
Classifier: Programming Language :: Python :: 3.10
Classifier: Programming Language :: C++
Classifier: Intended Audience :: Science/Research
Classifier: Programming Language :: Python :: Implementation :: CPython
Classifier: Operating System :: POSIX :: Linux
License-File: LICENSE.txt
